CHANGELOG.rst
LICENSE
MANIFEST.in
README.rst
html5-print
pytest.ini
requirements.txt
setup.py
html5print/__init__.py
html5print/cssprint.py
html5print/html5print.py
html5print/jsprint.py
html5print/utils.py
html5print.egg-info/PKG-INFO
html5print.egg-info/SOURCES.txt
html5print.egg-info/dependency_links.txt
html5print.egg-info/requires.txt
html5print.egg-info/top_level.txt
html5print/test/test_cssEncoding.py
html5print/test/test_decodeFunc.py
html5print/test/test_doctestBug.py
html5print/test/test_html5print.py
html5print/test/test_jsprint.py
html5print/test/test_returntype.py
html5print/test/fixture/failed_detection.js
html5print/test/fixture/unicode_sample.css
html5print/test/fixture/unicode_sample.html
html5print/test/fixture/unicode_sample.js
test/script.py
test/test_html5-print.py
test/fixture/unicode_sample.css
test/fixture/unicode_sample.html
test/fixture/unicode_sample.js